compas_bender/__init__.py
compas_bender/__main__.py
compas_bender/install.py
compas_bender/bend/__init__.py
compas_bender/bend/bend_splines.py
compas_bender/datastructures/__init__.py
compas_bender/datastructures/bendnetwork.py
compas_bender/notebook/__init__.py
compas_bender/notebook/scene/__init__.py
compas_bender/scene/__init__.py
compas_bender-0.1.1.dist-info/LICENSE
compas_bender-0.1.1.dist-info/METADATA
compas_bender-0.1.1.dist-info/WHEEL
compas_bender-0.1.1.dist-info/top_level.txt
compas_bender-0.1.1.dist-info/RECORD
