Metadata-Version: 2.1
Name: compas_bender
Version: 0.1.1
Summary: Form Finding of bending active structures using a modified dynamic relaxation method.
Author-email: tom van mele <tom.v.mele@gmail.com>
License: MIT License
Project-URL: Homepage, https://blockresearchgroup.github.io/compas_bender
Project-URL: Documentation, https://blockresearchgroup.github.io/compas_bender
Project-URL: Repository, https://github.com/blockresearchgroup/compas_bender.git
Project-URL: Changelog, https://github.com/blockresearchgroup/compas_bender/blob/main/CHANGELOG.md
Classifier: Development Status :: 4 - Beta
Classifier: Topic :: Scientific/Engineering
Classifier: Programming Language :: Python
Classifier: Programming Language :: Python :: 3
Classifier: Programming Language :: Python :: 3.9
Classifier: Programming Language :: Python :: 3.10
Classifier: Programming Language :: Python :: 3.11
Requires-Python: >=3.9
License-File: LICENSE
Requires-Dist: compas >=2.0
Provides-Extra: dev
Requires-Dist: attrs >=17.4 ; extra == 'dev'
Requires-Dist: black >=22.12.0 ; extra == 'dev'
Requires-Dist: bump-my-version ; extra == 'dev'
Requires-Dist: compas-invocations2 ; extra == 'dev'
Requires-Dist: compas-notebook ; extra == 'dev'
Requires-Dist: invoke >=0.14 ; extra == 'dev'
Requires-Dist: ruff ; extra == 'dev'
Requires-Dist: sphinx-compas2-theme ; extra == 'dev'
Requires-Dist: twine ; extra == 'dev'
Requires-Dist: wheel ; extra == 'dev'
